summary/__init__.py
summary/summary.py
utils/__init__.py
utils/helpers.py
diagnet-0.0.5.dist-info/LICENSE
diagnet-0.0.5.dist-info/METADATA
diagnet-0.0.5.dist-info/WHEEL
diagnet-0.0.5.dist-info/entry_points.txt
diagnet-0.0.5.dist-info/top_level.txt
diagnet-0.0.5.dist-info/RECORD
