Metadata-Version: 2.1
Name: diagnet
Version: 0.0.5
Summary: A python network diagnosis tool
Home-page: https://github.com/slowpoke1214/Diagnet
Author: Joey Kennedy
Author-email: joey.s.k.kennedy@gmail.com
License: UNKNOWN
Platform: UNKNOWN
Classifier: Programming Language :: Python :: 3
Classifier: License :: OSI Approved :: MIT License
Classifier: Operating System :: OS Independent
Requires-Python: >=3.6
Requires-Dist: scapy (>=2.4.3)
Requires-Dist: prettytable (>=2.1.0)
